stara_maze_generator/__init__.py
stara_maze_generator/cli.py
stara_maze_generator/pathfinder/__init__.py
stara_maze_generator/pathfinder/base.py
stara_maze_generator/pathfinder/bfs.py
stara_maze_generator/pathfinder/types.py
stara_maze_generator/visualization.py
stara_maze_generator/vmaze.py
stara_maze_generator-0.2.2.dist-info/LICENSE
stara_maze_generator-0.2.2.dist-info/METADATA
stara_maze_generator-0.2.2.dist-info/WHEEL
stara_maze_generator-0.2.2.dist-info/entry_points.txt
stara_maze_generator-0.2.2.dist-info/RECORD
