Metadata-Version: 2.3
Name: stara-maze-generator
Version: 0.2.2
Summary: Creating mazes using prims' algorithm for the stara project
Author: Valerius Mattfeld
Author-email: v.mattfeld@stud.uni-goettingen.de
Requires-Python: >=3.12,<4.0
Classifier: Programming Language :: Python :: 3
Classifier: Programming Language :: Python :: 3.12
Classifier: Programming Language :: Python :: 3.13
Requires-Dist: loguru (>=0.7.3,<0.8.0)
Requires-Dist: numpy (>=2.2.1,<3.0.0)
